[
    {
        "id": "email.open",
        "title": "Emails opened",
        "type": "Basic",
        "description": "Number of users with at least one visit during the period, meaning the number of users during the period."
    },
    {
        "id": "user.signup",
        "title": "New Users",
        "type": "Basic",
        "description": "Number of users that start on this platform."
    },
    {
        "id": "user.info",
        "title": "User info",
        "type": "General",
        "description": "Number of users with at least one visit to us during the period."
    },
    {
        "id": "email.track.created",
        "title": "Email track created",
        "type": "General",
        "description": "Number of users with at least one visit to us during the period."
    },
    {
        "id": "crx.uninstall",
        "title": "Chrome extension uninstalled",
        "type": "General",
        "description": "Number of users with at least one visit to us during the period."
    },
    {
        "id": "user.acquired",
        "title": "User acquired",
        "type": "General",
        "description": "Number of users with at least one visit to us during the period."
    }
]
